appletun/__init__.py
appletun/__main__.py
appletun/_version.py
appletun-0.0.5.dist-info/licenses/LICENSE
appletun-0.0.5.dist-info/METADATA
appletun-0.0.5.dist-info/WHEEL
appletun-0.0.5.dist-info/entry_points.txt
appletun-0.0.5.dist-info/top_level.txt
appletun-0.0.5.dist-info/RECORD
