Metadata-Version: 2.4
Name: AppleTun
Version: 0.0.5
Summary: A utility for creating and connecting to a local VPN for ios devices allowing HTTP proxy without device supervision for all connections (not limited to Wi-Fi)
Author-email: zqxwce <yyyyyy6yyyyyy6@gmail.com>
Maintainer-email: zqxwce <yyyyyy6yyyyyy6@gmail.com>
License:                     GNU GENERAL PUBLIC LICENSE
Project-URL: Homepage, https://github.com/zqxwce/appletun
Project-URL: Bug Reports, https://github.com/zqxwce/appletun/issues
Keywords: ios,cli,preferences,appletun,VPN,http,proxy
Classifier: Development Status :: 5 - Production/Stable
Classifier: License :: OSI Approved :: GNU General Public License v3 or later (GPLv3+)
Classifier: Programming Language :: Python :: 3
Classifier: Programming Language :: Python :: 3.9
Classifier: Programming Language :: Python :: 3.10
Classifier: Programming Language :: Python :: 3.11
Classifier: Programming Language :: Python :: 3.12
Classifier: Programming Language :: Python :: 3.13
Classifier: Programming Language :: Python :: 3 :: Only
Requires-Python: >=3.9
License-File: LICENSE
Requires-Dist: pymobiledevice3>=7.0.7
Requires-Dist: click
Requires-Dist: plumbum
Requires-Dist: psutil
Dynamic: license-file
